CHANGES.rst
LICENSE
MANIFEST.in
README.rst
requirements.txt
setup.py
greenwich/__init__.py
greenwich/base.py
greenwich/geometry.py
greenwich/io.py
greenwich/layer.py
greenwich/raster.py
greenwich/srs.py
greenwich/tile.py
greenwich.egg-info/PKG-INFO
greenwich.egg-info/SOURCES.txt
greenwich.egg-info/dependency_links.txt
greenwich.egg-info/requires.txt
greenwich.egg-info/top_level.txt