Metadata-Version: 1.1
Name: greenwich
Version: 0.8.0
Summary: A GDAL wrapper with Python conveniences
Home-page: https://github.com/bkg/greenwich
Author: Brian Galey
Author-email: bkgaley@gmail.com
License: BSD
Platform: UNKNOWN
Classifier: Development Status :: 4 - Beta
Classifier: Intended Audience :: Developers
Classifier: License :: OSI Approved :: BSD License
Classifier: Natural Language :: English
Classifier: Programming Language :: Python :: 2
Classifier: Programming Language :: Python :: 2.7
Classifier: Programming Language :: Python :: 3
Classifier: Programming Language :: Python :: 3.5
